StockSpider/DATA_USE.py
StockSpider/HolderSpider.py
StockSpider/MarketOverviewSpider.py
StockSpider/NameCodeInterpreter.py
StockSpider/StockSpider.py
StockSpider/__init__.py
StockSpider/__version__.py
StockSpider/core.py
StockSpider/core2.py
StockSpider/newsSpider.py
StockSpider/smSpider.py
CStockSpider-0.2.21.dist-info/LICENSE
CStockSpider-0.2.21.dist-info/METADATA
CStockSpider-0.2.21.dist-info/WHEEL
CStockSpider-0.2.21.dist-info/top_level.txt
CStockSpider-0.2.21.dist-info/RECORD
