Metadata-Version: 2.1
Name: CStockSpider
Version: 0.2.21
Summary: A module for fetching stock info and public stock company in China
Home-page: https://github.com/me/myproject
Author: Leo
Author-email: me@example.com
License: MIT
Platform: UNKNOWN
Classifier: License :: OSI Approved :: MIT License
Classifier: Programming Language :: Python
Classifier: Programming Language :: Python :: 3
Classifier: Programming Language :: Python :: 3.6
Classifier: Programming Language :: Python :: Implementation :: CPython
Classifier: Programming Language :: Python :: Implementation :: PyPy
Requires-Python: >=3.7.0
License-File: LICENSE
Requires-Dist: requests
Requires-Dist: pandas
Requires-Dist: lxml
Requires-Dist: gensim
Requires-Dist: numpy
Requires-Dist: jieba
